Workbook

Sheet Fuente_Hoja1
A1: Variable | B1: Definición | C1: Detalle | D1: Negocios Internacionales | E1: Software | F1: Enfermería | G1: Medicina | H1: Odontología | I1: Multimedia y produccion audiovisual | J1: Derecho | K1: Arquitectura | L1: RRII | M1: Gastronomía | N1: Música | O1: Psicología
A2: Matriculados | B2: Tasa de crecimiento promedio del número de estudiantes matriculados en el programa propuesto o en programas similares | C2: Tasa de crecimiento de matriculados del periodo 2020-2025 | D2: 0.38425479 | E2: 0.06 | F2: 0.2823008 | G2: 0.1251916 | H2: 0.14733214 | I2: 0.6607827 | J2: 0.14716569 | K2: 0.1227361 | L2: 0.12305802 | M2: 0.17657126 | N2: -0.50057452 | O2: 0.15764233
A3: Titulados | B3: Tasa de crecimiento promedio del número de estudiantes titulados en el programa propuesto o en programas similares | C3: Tasa de crecimiento de titulados del periodo 2020-2025 | D3: 0.31495682 | E3: 1.616788 | F3: 0.077762276 | G3: 0.030541698 | H3: 0.078305724 | I3: -0.2402547 | J3: 0.30614306 | K3: 0.17986311 | L3: 0.3334193 | M3: 0.11452712 | N3: -0.36223861 | O3: 0.22059947
A4: Cantidad de búsquedas web | B4: Volumen de búsquedas en Google Trends a nivel local utilizado para medir la evolución del interés del nombre en el tiempo. | C4: Volumen de busquedas web en google trends sobre 100 para Ecuador | D4: 36.714286 | E4: 18.285714 | F4: 81 | G4: 74.285714 | H4: 74.857143 | I4: 24.571429 | J4: 65.142857 | K4: 62.714286 | L4: 14 | M4: 59.571429 | N4: 40.285714 | O4: 48.714286
A5: Cantidad de búsquedas web | B5: Volumen de búsquedas en Google Trends a nivel regional utilizado para medir la evolución del interés del nombre en el tiempo. | C5: Promedio de volumen de busquedas web en google trends sobre 100 para Países de lationamerica | D5: 27.178571 | E5: 15.817143 | F5: 58.704286 | G5: 60.367143 | H5: 66.901429 | I5: 21.111429 | J5: 58.275714 | K5: 54.284286 | L5: 13.291429 | M5: 41.648571 | N5: 23.881429 | O5: 45.648571
A6: Cantidad de búsquedas web | B6: Volumen de búsquedas en Google Trends a nivel mundial utilizado para medir la evolución del interés del nombre en el tiempo. | C6: Promedio de volumen de busquedas web en google trends sobre 100 para Países con datos del mundoo incluido lationamerica | D6: 23.294286 | E6: 20.812857 | F6: 56.138571 | G6: 45.137143 | H6: 56.388571 | I6: 19.678571 | J6: 54.925714 | K6: 43.285714 | L6: 22.125714 | M6: 37.871429 | N6: 24.67 | O6: 43.905714
A7: Palabras clave | B7: Nivel promedio de interés de búsqueda de las palabras clave relacionadas con el programa durante los últimos 12 meses a nivel local | C7: Promedio de busquedas web con respecto al nombre de la carrera en ecuador durante los ultimos 12 meses | D7: 17.5 | E7: 23.833333 | F7: 11.333333 | G7: 10.333333 | H7: 11.833333 | I7: 12.333333 | J7: 10 | K7: 15.166667 | L7: 12.5 | M7: 10.5 | N7: 16.666667 | O7: 11.833333
A8: Calificación nombre | B8: Evaluación del potencial del nombre propuesto según claridad, actualidad, atractivo comercial, profesionalismo académico e internacionalización | C8: Calificación sobre e13,58 dada por una IA especializada que mide el atractivo del programa | D8: 12.804 | E8: 12.804 | F8: 12.028 | G8: 11.64 | H8: 11.64 | I8: 12.416 | J8: 11.64 | K8: 12.028 | L8: 12.804 | M8: 11.64 | N8: 12.416 | O8: 12.028
A9: Cantidad de profesionales | B9: Cantidad de profesionales en Ecuador cuyos cargos o industrias se relacionan con el campo de la carrera | C9: Cantidad de profesionales registrados en linkedin que responden a cargos relacionados con la carrera propuesta | D9: 120 | E9: 21054 | F9: 30236 | G9: 24343 | H9: 10430 | I9: 8651 | J9: 30280 | K9: 10806 | L9: 126 | M9: 11671 | N9: 3730 | O9: 14080
A10: Cantidad de vacantes | B10: Cantidad de vacantes disponibles en Ecuador relacionadas con los cargos o áreas profesionales vinculadas a la carrera | C10: Cantidad de vacantes publicadas en linkedin con relación a las carreras propuestas | D10: 1 | E10: 194 | F10: 12 | G10: 21 | H10: 7 | I10: 9 | J10: 9 | K10: 10 | L10: 1 | M10: 11 | N10: 1 | O10: 6
A11: Brecha Mercado Laboral vs Programa Educativo | B11: Grado de coincidencia entre las aptitudes del programa y las demandadas por el mercado laboral, identificando posibles brechas de ajuste | C11: Calificación sobre 100% de una IA especializada que compara las aptitudes actuales en el mercado laboral desde LinkedIn con las aptitudes propuestas por programa a fin de conocer su alineación | D11: 0.95 | E11: 0.7 | F11: 0.97 | G11: 0.95 | H11: 0.9 | I11: 0.85 | J11: 0.97 | K11: 0.82 | L11: 0.97 | M11: 0.9 | N11: 0.85 | O11: 0.85
A12: Salario Promedio | B12: Nivel de remuneración promedio asociado al campo laboral de la carrera, estimado a partir de fuentes públicas y de las actividades económicas vinculadas mediante códigos CIIU | C12: Salario promedio por CIIU identificado en la REES | D12: 982.17 | E12: 1276.95 | F12: 739.35 | G12: 1135.43 | H12: 1135.43 | I12: 784 | J12: 721.87 | K12: 804.64 | L12: 1516.06 | M12: 577.89 | N12: 855.11 | O12: 727.66
A13: Cantidad de oferta | B13: Nivel de presencia de universidades que ofertan la carrera o programas similares, contrastado con el nivel de interés del mercado | C13: Cantidad de universidades privadas de la sierra que ofertan la carrera | D13: 10 | E13: 9 | F13: 10 | G13: 14 | H13: 12 | I13: 5 | J13: 15 | K13: 11 | L13: 6 | M13: 10 | N13: 4 | O13: 13
... A16: Sociedades y Naturales | B16: Valor de las ventas de bienes y servicios realizadas por sociedades que están sujetas a IVA. | C16: Acumulado de los ultimos 36 meses de ventas gravadas para sociedadess de los ciius identificados para cada carrera | D16: 7.4218948e+08 | E16: 4.3225481e+08 | F16: 2.7095366e+08 | G16: 96188194 | H16: 2497795.9 | I16: 26815816 | J16: 2.5296972e+09 | K16: 1.030132e+09 | L16: 360282.75 | M16: 2.8350526e+08 | N16: 269825.34 | O16: 94330062

Sheet Fuente_PRECIO
A1: Carrera | B1: Precio promedio | C1: Mediana mercado | D1: Registros | G1: precios udla | H1: promedio | I1: mediana | L1: FACULTAD | M1: PROMEDIO | N1: MEDIANA | O1: MPROMEDIO | P1: MMEDIANA | Q1: DIFERENCIA promedio | R1: diferencia mediana | S1: FACULTAD
A2: Arquitectura | B2: 3484.49 | C2: 2945.58 | D2: 13 | G2: ARQUITECTURA | H2: 3673.32 | I2: 3715.98 | L2: ARQUITECTURA | M2: 3673.32 | N2: 3715.98 | O2: 3484.49 | P2: 2945.58 | Q2: 0.054191575 | R2: 0.26154442 | S2: ARQUITECTURA
A3: Derecho | B3: 2326.38 | C3: 1709.5 | D3: 20 | G3: DERECHO | H3: 3484.02 | I3: 3484.02 | L3: DERECHO | M3: 3484.02 | N3: 3484.02 | O3: 2326.38 | P3: 1709.5 | Q3: 0.49761432 | R3: 1.0380345 | S3: DERECHO
A4: Enfermería | B4: 2990.57 | C4: 2661.5 | D4: 8 | G4: SALUD | H4: 3067.66 | I4: 3064.98 | L4: SALUD | M4: 3067.66 | N4: 3064.98 | O4: 2990.57 | P4: 2661.5 | Q4: 0.025777695 | R4: 0.15159872 | S4: SALUD
A5: Gastronomía | B5: 2439.68 | C5: 1672 | D5: 11 | G5: GASTRONOMIA | H5: 3823.02 | I5: 3823.02 | L5: GASTRONOMIA | M5: 3823.02 | N5: 3823.02 | O5: 2439.68 | P5: 1672 | Q5: 0.56701699 | R5: 1.2864952 | S5: GASTRONOMIA
A6: Medicina | B6: 3942.79 | C6: 3225 | D6: 11 | G6: MEDICINA | H6: 4824 | I6: 4824 | L6: MEDICINA | M6: 4824 | N6: 4824 | O6: 3942.79 | P6: 3225 | Q6: 0.2234991 | R6: 0.49581395 | S6: MEDICINA
A7: Multimedia y Producción Audiovisual | B7: 2204.49 | C7: 1953.82 | D7: 5 | G7: NODO | H7: 3527.11 | I7: 3484.02 | L7: NODO | M7: 3527.11 | N7: 3484.02 | O7: 2204.49 | P7: 1953.82 | Q7: 0.59996643 | R7: 0.78318371 | S7: NODO
A8: Música | B8: 4572 | C8: 4345 | D8: 3 | G8: MUSICA | H8: 3588 | I8: 3588 | L8: MUSICA | M8: 3588 | N8: 3588 | O8: 4572 | P8: 4345 | Q8: -0.2152231 | R8: -0.17422325 | S8: MUSICA
A9: Negocios Internacionales | B9: 3414.22 | C9: 3828 | D9: 9 | G9: FACEA | H9: 3487.518 | I9: 3484.02 | L9: FACEA | M9: 3487.518 | N9: 3484.02 | O9: 3414.22 | P9: 3828 | Q9: 0.021468447 | R9: -0.089858934 | S9: FACEA
A10: Odontología | B10: 3909.03 | C10: 3766.5 | D10: 10 | G10: ODONTOLOGIA | H10: 4171.02 | I10: 4171.02 | L10: ODONTOLOGIA | M10: 4171.02 | N10: 4171.02 | O10: 3909.03 | P10: 3766.5 | Q10: 0.067021742 | R10: 0.10739944 | S10: ODONTOLOGIA
A11: Psicología | B11: 2735.16 | C11: 2164.16 | D11: 23 | G11: PSICOLOGIA | H11: 2808.9867 | I11: 3334.98 | L11: PSICOLOGIA | M11: 2808.9867 | N11: 3334.98 | O11: 2735.16 | P11: 2164.16 | Q11: 0.026991718 | R11: 0.54100436 | S11: PSICOLOGIA
A12: Relaciones Internacionales | B12: 3340 | C12: 4175 | D12: 5 | G12: CIENCIAS POL | H12: 3480 | I12: 3480 | L12: CIENCIAS POL | M12: 3480 | N12: 3480 | O12: 3340 | P12: 4175 | Q12: 0.041916168 | R12: -0.16646707 | S12: CIENCIAS POL
A13: Software | B13: 1574.14 | C13: 1650 | D13: 9 | G13: FICA | H13: 3360.6046 | I13: 3484.02 | L13: FICA | M13: 3360.6046 | N13: 3484.02 | O13: 1684.35 | P13: 1520 | Q13: 0.99519376 | R13: 1.2921184 | S13: FICA
C14: udla | D14: promedio
A15: Arquitectura | B15: 598 | C15: 3588 | D15: 3484.49 | E15: 0.029705925 | F15: Arquitectura
A16: Derecho | B16: 580.67 | C16: 3484.02 | D16: 2326.38 | E16: 0.49761432 | F16: Derecho
A17: Enfermería | B17: 403.67 | C17: 2422.02 | D17: 2990.57 | E17: -0.19011426 | F17: Enfermería
A18: Gastronomía | B18: 637.17 | C18: 3823.02 | D18: 2439.68 | E18: 0.56701699 | F18: Gastronomía
A19: Medicina | B19: 804 | C19: 4824 | D19: 3942.79 | E19: 0.2234991 | F19: Medicina
A20: Multimedia y Producción Audiovisual | B20: 572.17 | C20: 3433.02 | D20: 2204.49 | E20: 0.55728536 | F20: Multimedia y Producción Audiovisual
A21: Música | B21: 598 | C21: 3588 | D21: 4572 | E21: -0.2152231 | F21: Música
A22: Negocios Internacionales | B22: 580.67 | C22: 3484.02 | D22: 3414.22 | E22: 0.020443908 | F22: Negocios Internacionales
A23: Odontología | B23: 695.17 | C23: 4171.02 | D23: 3909.03 | E23: 0.067021742 | F23: Odontología
A24: Psicología | B24: 555.83 | C24: 3334.98 | D24: 2735.16 | E24: 0.21929979 | F24: Psicología
A25: Relaciones Internacionales | B25: 580.67 | C25: 3484.02 | D25: 3340 | E25: 0.04311976 | F25: Relaciones Internacionales
A26: Software | B26: 525.5 | C26: 3153 | D26: 1574.14 | E26: 1.0029985 | F26: Software
A31: Arquitectura | B31: https://www.udla.edu.ec/estudios/pregrado/arquitectura/
A32: Derecho | B32: https://www.udla.edu.ec/estudios/pregrado/derecho/
A33: Enfermería | B33: https://www.udla.edu.ec/estudios/pregrado/enfermeria/
A34: Gastronomía | B34: https://www.udla.edu.ec/estudios/pregrado/gastronomia/
A35: Medicina | B35: https://www.udla.edu.ec/estudios/pregrado/medicina/
A36: Multimedia y Producción Audiovisual | B36: https://www.udla.edu.ec/estudios/pregrado/multimedia-y-produccion-audiovisual/
A37: Música | B37: https://www.udla.edu.ec/estudios/pregrado/musica/
A38: Negocios Internacionales | B38: https://www.udla.edu.ec/estudios/pregrado/negocios-internacionales/
A39: Odontología | B39: https://www.udla.edu.ec/estudios/pregrado/odontologia/
A40: Psicología | B40: https://www.udla.edu.ec/estudios/pregrado/psicologia/
A41: Relaciones Internacionales | B41: https://www.udla.edu.ec/estudios/pregrado/relaciones-internacionales/
A42: Software | B42: https://www.udla.edu.ec/estudios/pregrado/software/

Sheet Fuente_Hoja4
A1: CARRERA | B1: PALABRA_CLAVE | C1: VALOR
A2: SOFTWARE | B2: Desarrollo | C2: 56 | E2: DERECHO | F2: Filosofía del derecho | G2: 16 | I2: MEDICINA | J2: Farmacología | K2: 12 | M2: MUSICA | N2: Canto | O2: 34 | Q2: GASTRONOMIA | R2: Chocolatería | S2: 12
A3: SOFTWARE | B3: Redes | C3: 30 | E3: DERECHO | F3: Derecho Empresarial | G3: 10 | I3: MEDICINA | J3: Semiología | K3: 11 | M3: MUSICA | N3: Historia de la música | O3: 15 | Q3: GASTRONOMIA | R3: Cocina Internacional | S3: 12
A4: SOFTWARE | B4: Desarrollo de videojuegos | C4: 15 | E4: DERECHO | F4: Derecho Laboral | G4: 9 | I4: MEDICINA | J4: Tropical medicine | K4: 11 | M4: MUSICA | N4: Interpretación | O4: 14 | Q4: GASTRONOMIA | R4: Dietética y nutrición | S4: 12
A5: SOFTWARE | B5: Seguridad Informática | C5: 15 | E5: DERECHO | F5: Garantías Constitucionales | G5: 9 | I5: MEDICINA | J5: Quirúrgica | K5: 10 | M5: MUSICA | N5: Composición | O5: 13 | Q5: GASTRONOMIA | R5: Cárnicos | S5: 9
A6: SOFTWARE | B6: Algoritmo | C6: 14 | E6: DERECHO | F6: Deontología Jurídica | G6: 8 | I6: MEDICINA | J6: Morfofuncionales | K6: 9 | M6: MUSICA | N6: Instrumental | O6: 13 | Q6: GASTRONOMIA | R6: Cocina de vanguardia | S6: 9
A7: SOFTWARE | B7: Inteligencia Artificial | C7: 13 | E7: DERECHO | F7: Pluralismo Jurídico | G7: 8 | I7: MEDICINA | J7: Pediatría | K7: 9 | M7: MUSICA | N7: Armonía musical | O7: 11 | Q7: GASTRONOMIA | R7: Cocina Ecuatoriana | S7: 9
A8: SOFTWARE | B8: Programación | C8: 10 | E8: DERECHO | F8: Derecho Económico | G8: 7 | I8: MEDICINA | J8: Infectología | K8: 8 | M8: MUSICA | N8: Improvisación | O8: 11 | Q8: GASTRONOMIA | R8: Pastelería | S8: 9
A9: SOFTWARE | B9: Computación Ubicua | C9: 8 | E9: DERECHO | F9: Derecho Penal | G9: 7 | I9: MEDICINA | J9: Investigaciones Clínicas | K9: 8 | M9: MUSICA | N9: Ensamble | O9: 8 | Q9: GASTRONOMIA | R9: Alta cocina | S9: 8
A10: SOFTWARE | B10: Ingeniería Web | C10: 8 | E10: DERECHO | F10: Sujetos del Derecho | G10: 7 | I10: MEDICINA | J10: Medicina Legal | K10: 5 | M10: MUSICA | N10: Proyecto Artístico | O10: 8 | Q10: GASTRONOMIA | R10: Panadería | S10: 8
A11: SOFTWARE | B11: Procesador | C11: 7 | E11: DERECHO | F11: Teoría del delito | G11: 7 | I11: MEDICINA | J11: Microbiología | K11: 5 | M11: MUSICA | N11: Producción musical | O11: 6 | Q11: GASTRONOMIA | R11: Sanidad | S11: 7
C12: 23.833333 | D12: 17.6 | G12: 10 | H12: 8.8 | K12: 10.333333 | L12: 8.8 | O12: 16.666667 | P12: 13.3 | S12: 10.5 | T12: 9.5
A14: RELACIONES INTERNACIONALES | B14: Derechos Humanos | C14: 18 | E14: NEGOCIOS INTERNACIONALES | F14: Contabilidad | G14: 42 | I14: ARQUITECTURA | J14: Maquetería | K14: 24 | M14: MULTIMEDIA Y PRODUCCION AUDIOVISUAL | N14: Interfaces | O14: 15 | Q14: ENFERMERIA | R14: Clínica enfermería | S14: 15
A15: RELACIONES INTERNACIONALES | B15: Políticas Públicas | C15: 14 | E15: NEGOCIOS INTERNACIONALES | F15: Mercados Internacionales | G15: 15 | I15: ARQUITECTURA | J15: Construcción | K15: 19 | M15: MULTIMEDIA Y PRODUCCION AUDIOVISUAL | N15: Medios Digitales | O15: 13 | Q15: ENFERMERIA | R15: Enfermería en pacientes | S15: 13
A16: RELACIONES INTERNACIONALES | B16: Negociación | C16: 13 | E16: NEGOCIOS INTERNACIONALES | F16: Inteligencia de negocios | G16: 13 | I16: ARQUITECTURA | J16: Dibujo Natural | K16: 14 | M16: MULTIMEDIA Y PRODUCCION AUDIOVISUAL | N16: Diseño 3D | O16: 12 | Q16: ENFERMERIA | R16: Gestión de calidad | S16: 12
A17: RELACIONES INTERNACIONALES | B17: Regionalismos | C17: 13 | E17: NEGOCIOS INTERNACIONALES | F17: Dirección Estratégica | G17: 12 | I17: ARQUITECTURA | J17: Dibujo Técnico | K17: 12 | M17: MULTIMEDIA Y PRODUCCION AUDIOVISUAL | N17: Edición de video | O17: 12 | Q17: ENFERMERIA | R17: Salud comunitaria | S17: 10
A18: RELACIONES INTERNACIONALES | B18: Política Mundial | C18: 9 | E18: NEGOCIOS INTERNACIONALES | F18: Negociación | G18: 12 | I18: ARQUITECTURA | J18: Sostenibilidad Ambiental | K18: 11 | M18: MULTIMEDIA Y PRODUCCION AUDIOVISUAL | N18: Animación Digital | O18: 11 | Q18: ENFERMERIA | R18: Bioestadística | S18: 9
A19: RELACIONES INTERNACIONALES | B19: Estado y constitución | C19: 8 | E19: NEGOCIOS INTERNACIONALES | F19: Comercio Exterior | G19: 11 | I19: ARQUITECTURA | J19: Urbanismo | K19: 11 | M19: MULTIMEDIA Y PRODUCCION AUDIOVISUAL | N19: Dirección de Arte | O19: 11 | Q19: ENFERMERIA | R19: Servicios de emergencia | S19: 9
A20: RELACIONES INTERNACIONALES | B20: Geopolítica | C20: 7 | E20: NEGOCIOS INTERNACIONALES | F20: Estrategia De Promoción | G20: 6 | I20: ARQUITECTURA | J20: Arquitectura del paisaje | K20: 10 | M20: MULTIMEDIA Y PRODUCCION AUDIOVISUAL | N20: Render | O20: 11 | Q20: ENFERMERIA | R20: Bioética | S20: 7
A21: RELACIONES INTERNACIONALES | B21: Organismos Internacionales | C21: 7 | E21: NEGOCIOS INTERNACIONALES | F21: Gestión de proyectos | G21: 6 | I21: ARQUITECTURA | J21: Proyectos arquitectónicos | K21: 8 | M21: MULTIMEDIA Y PRODUCCION AUDIOVISUAL | N21: Producción Audiovisual | O21: 9 | Q21: ENFERMERIA | R21: Cuidados del adulto mayor | S21: 7
A22: RELACIONES INTERNACIONALES | B22: Administración pública | C22: 6 | E22: NEGOCIOS INTERNACIONALES | F22: Inteligencia de mercados | G22: 6 | I22: ARQUITECTURA | J22: Taller de diseño | K22: 7 | M22: MULTIMEDIA Y PRODUCCION AUDIOVISUAL | N22: Rigging | O22: 9 | Q22: ENFERMERIA | R22: Fisiopatología | S22: 6
A23: RELACIONES INTERNACIONALES | B23: Economía Política | C23: 5 | E23: NEGOCIOS INTERNACIONALES | F23: Exportaciones e importaciones | G23: 5 | I23: ARQUITECTURA | J23: Diseño Arquitectonico | K23: 6 | M23: MULTIMEDIA Y PRODUCCION AUDIOVISUAL | N23: Efectos especiales | O23: 8 | Q23: ENFERMERIA | R23: Instrumentación quirúrgica | S23: 6
C24: 12.5 | D24: 10 | G24: 17.5 | H24: 12.8 | K24: 15.166667 | L24: 12.2 | O24: 12.333333 | P24: 11.1 | S24: 11.333333 | T24: 9.4
A26: ODONTOLOGIA | B26: Estomatología | C26: 14 | E26: PSICOLOGIA | F26: Conciencia | G26: 19
A27: ODONTOLOGIA | B27: Embriología | C27: 13 | E27: PSICOLOGIA | F27: Psicopatología | G27: 11
A28: ODONTOLOGIA | B28: Odontopediatría | C28: 12 | E28: PSICOLOGIA | F28: Psicoterapia | G28: 11
A29: ODONTOLOGIA | B29: Ortodoncia | C29: 12 | E29: PSICOLOGIA | F29: Procesos de cambio | G29: 10
A30: ODONTOLOGIA | B30: Imagenología | C30: 10 | E30: PSICOLOGIA | F30: Psicofarmacología | G30: 10
A31: ODONTOLOGIA | B31: Periodoncia | C31: 10 | E31: PSICOLOGIA | F31: Psiquiatría | G31: 10
A32: ODONTOLOGIA | B32: Protesis Dental | C32: 10 | E32: PSICOLOGIA | F32: Psicología del consumidor | G32: 8
A33: ODONTOLOGIA | B33: Anatomía patológica | C33: 9 | E33: PSICOLOGIA | F33: Psicología educativa | G33: 8
A34: ODONTOLOGIA | B34: Biomateriales | C34: 9 | E34: PSICOLOGIA | F34: Psicología comunitaria | G34: 7
A35: ODONTOLOGIA | B35: Endodoncia | C35: 6 | E35: PSICOLOGIA | F35: Psicología de la personalidad | G35: 6
C36: 11.833333 | D36: 10.5 | G36: 11.833333 | H36: 10
A49: 17738 | B49: 20328 | C49: 21793 | D49: 21815 | E49: 22312

Sheet Guía
A1: Tema | B1: Criterio / limitación
A2: Alcance | B2: Comparativo exploratorio de 11 carreras contra Negocios Internacionales. No estima probabilidad de éxito ni viabilidad financiera de apertura.
A3: Referencia | B3: Negocios Internacionales, elegida por el usuario por desempeño satisfactorio y estable. No se asume que sea el promedio estadístico.
A4: Pesos | B4: Se conservan 30%, 22%, 28%, 12%, 8%. Competencia pasa íntegramente a oportunidad de mercado; el precio se mide una sola vez en el bloque de 12%. Pagador/capacidad de pago se excluye por falta de datos.
A5: Modalidad pendiente | B5: Recordatorio: revisar modalidad y capacidad de implementación en una fase posterior. Presencial como supuesto descriptivo; no entra al cálculo.
A6: Datos utilizados | B6: Hoja1: búsquedas locales (fila 4), sin palabras clave ni promedios regional/mundial. Brecha de precio: fila 14. Ventas: suma de filas 15 y 16.
A7: Precio: discrepancias | B7: Hoja1 y PRECIO contienen brechas distintas, especialmente Enfermería, Psicología y Multimedia. Se utiliza Hoja1 sin sustituirla con promedios de facultad. Conciliar antes de decidir.
A8: Google Trends: validación pendiente | B8: No está documentado si las carreras comparten escala de consulta o un ancla común. Los índices 0–100 se utilizan provisionalmente como comparables; todos los resultados quedan sujetos a validar esa extracción.
A9: Laboral: validación pendiente | B9: Negocios tiene 120 profesionales y 1 vacante frente a universos mucho mayores en otras carreras. Verificar equivalencia de búsquedas. Vacantes/profesionales es una señal relativa, no una tasa de empleabilidad.
A10: Economía | B10: La base contiene ventas acumuladas de 36 meses, no tasas de crecimiento. El bloque mide tamaño económico asociado, con transformación logarítmica; no crecimiento. Revisar mapeo CIIU y solapamientos.
A11: Normalización | B11: Referencia = 70 puntos por indicador. Variables positivas: MIN(100,140*x/(x+referencia)). Crecimientos: limitar a 0–100 el valor 70+50*(x-referencia), usando tasas decimales. No dividir crecimientos negativos.
A12: Competencia y oportunidad | B12: Puntaje de menor competencia: MIN(100,140*competidores_ref/(competidores+competidores_ref)). Oportunidad=MIN(puntaje_demanda,RAIZ(puntaje_demanda*puntaje_competencia)). La demanda limita el puntaje: pocos competidores no compensan bajo interés.
... A19: Edición | B19: Datos y Parámetros son editables. Puntajes y Resultados tienen fórmulas y valores calculados guardados. El libro se recalcula al abrir. Mantener la fila 2 de Datos como referencia.

Sheet Parámetros
A1: Parámetro | B1: Valor
A2: Demanda e interés | B2: 0.3
A3: Empleabilidad y valor | B3: 0.22
A4: Oportunidad de mercado | B4: 0.28
A5: Precio frente al mercado | B5: 0.12
A6: Tamaño del sector económico | B6: 0.08
A7: Demanda del nombre dentro de demanda | B7: 0.65
A8: Búsquedas dentro del nombre | B8: 0.9
A9: Matriculados dentro de demanda educativa | B9: 0.7
A10: Vacantes/profesionales dentro de empleabilidad | B10: 0.4
A11: Alineación dentro de empleabilidad | B11: 0.35
A12: Ancla de referencia | B12: 70
A13: Pendiente crecimientos y precio | B13: 50
... A20: Mínimo empleabilidad y precio para priorizar | B20: 50
A22: Suma pesos bloques | B22: =SUM(B2:B6) -> 1

Sheet Datos
A1: Carrera | B1: Crecimiento matriculados | C1: Crecimiento titulados | D1: Búsquedas locales | E1: Calificación nombre | F1: Profesionales | G1: Vacantes | H1: Alineación | I1: Salario | J1: Competidores | K1: Brecha precio vs media | L1: Ventas naturales | M1: Ventas sociedades
A2: Negocios Internacionales | B2: 0.38425479 | C2: 0.31495682 | D2: 36.714286 | E2: 12.804 | F2: 120 | G2: 1 | H2: 0.95 | I2: 982.17 | J2: 10 | K2: 0.020443908 | L2: 1.6402023e+08 | M2: 7.4218948e+08
A3: Software | B3: 0.06 | C3: 1.616788 | D3: 18.285714 | E3: 12.804 | F3: 21054 | G3: 194 | H3: 0.7 | I3: 1276.95 | J3: 9 | K3: 1.0029985 | L3: 26808346 | M3: 4.3225481e+08
A4: Enfermería | B4: 0.2823008 | C4: 0.077762276 | D4: 81 | E4: 12.028 | F4: 30236 | G4: 12 | H4: 0.97 | I4: 739.35 | J4: 10 | K4: -0.19011426 | L4: 70437974 | M4: 2.7095366e+08
A5: Medicina | B5: 0.1251916 | C5: 0.030541698 | D5: 74.285714 | E5: 11.64 | F5: 24343 | G5: 21 | H5: 0.95 | I5: 1135.43 | J5: 14 | K5: 0.2234991 | L5: 37942681 | M5: 96188194
A6: Odontología | B6: 0.14733214 | C6: 0.078305724 | D6: 74.857143 | E6: 11.64 | F6: 10430 | G6: 7 | H6: 0.9 | I6: 1135.43 | J6: 12 | K6: 0.067021742 | L6: 9011008.1 | M6: 2497795.9
A7: Multimedia y produccion audiovisual | B7: 0.6607827 | C7: -0.2402547 | D7: 24.571429 | E7: 12.416 | F7: 8651 | G7: 9 | H7: 0.85 | I7: 784 | J7: 5 | K7: 0.55728536 | L7: 7501947.4 | M7: 26815816
A8: Derecho | B8: 0.14716569 | C8: 0.30614306 | D8: 65.142857 | E8: 11.64 | F8: 30280 | G8: 9 | H8: 0.97 | I8: 721.87 | J8: 15 | K8: 0.49761432 | L8: 2.2477895e+09 | M8: 2.5296972e+09
A9: Arquitectura | B9: 0.1227361 | C9: 0.17986311 | D9: 62.714286 | E9: 12.028 | F9: 10806 | G9: 10 | H9: 0.82 | I9: 804.64 | J9: 11 | K9: 0.029705925 | L9: 3.4983104e+08 | M9: 1.030132e+09
A10: RRII | B10: 0.12305802 | C10: 0.3334193 | D10: 14 | E10: 12.804 | F10: 126 | G10: 1 | H10: 0.97 | I10: 1516.06 | J10: 6 | K10: 0.04311976 | L10: 99187.44 | M10: 360282.75
A11: Gastronomía | B11: 0.17657126 | C11: 0.11452712 | D11: 59.571429 | E11: 11.64 | F11: 11671 | G11: 11 | H11: 0.9 | I11: 577.89 | J11: 10 | K11: 0.56701699 | L11: 1.0510888e+08 | M11: 2.8350526e+08
A12: Música | B12: -0.50057452 | C12: -0.36223861 | D12: 40.285714 | E12: 12.416 | F12: 3730 | G12: 1 | H12: 0.85 | I12: 855.11 | J12: 4 | K12: -0.2152231 | L12: 1036967 | M12: 269825.34
A13: Psicología | B13: 0.15764233 | C13: 0.22059947 | D13: 48.714286 | E13: 12.028 | F13: 14080 | G13: 6 | H13: 0.85 | I13: 727.66 | J13: 13 | K13: 0.21929979 | L13: 598808.41 | M13: 94330062

Sheet Puntajes
A1: Carrera | B1: Matriculados | C1: Titulados | D1: Búsquedas | E1: Nombre | F1: Vacantes/profesionales | G1: Alineación | H1: Salario | I1: Menor competencia | J1: Oportunidad | K1: Precio | L1: Sector | M1: Demanda bloque | N1: Empleabilidad bloque
A2: Negocios Internacionales | B2: =MAX(0,MIN(100,'Parámetros'!$B$12+'Parámetros'!$B$13*(Datos!B2-Datos!$B$2))) -> 70 | C2: =MAX(0,MIN(100,'Parámetros'!$B$12+'Parámetros'!$B$13*(Datos!C2-Datos!$C$2))) -> 70 | D2: =MIN(100,2*'Parámetros'!$B$12*Datos!D2/(Datos!D2+Datos!$D$2)) -> 70 | E2: =MIN(100,2*'Parámetros'!$B$12*Datos!E2/(Datos!E2+Datos!$E$2)) -> 70 | F2: =MIN(100,2*'Parámetros'!$B$12*(Datos!G2/Datos!F2)/(Datos!G2/Datos!F2+Datos!$G$2/Datos!$F$2)) -> 70 | G2: =MIN(100,2*'Parámetros'!$B$12*Datos!H2/(Datos!H2+Datos!$H$2)) -> 70 | H2: =MIN(100,2*'Parámetros'!$B$12*Datos!I2/(Datos!I2+Datos!$I$2)) -> 70 | I2: =MIN(100,2*'Parámetros'!$B$12*Datos!$J$2/(Datos!J2+Datos!$J$2)) -> 70 | J2: =MIN(D2,SQRT(D2*I2)) -> 70 | K2: =MAX(0,MIN(100,'Parámetros'!$B$12-'Parámetros'!$B$13*(Datos!K2-Datos!$K$2))) -> 70 | L2: =MAX(0,MIN(100,'Parámetros'!$B$12+'Parámetros'!$B$14*LN((Datos!L2+Datos!M2)/(Datos!$L$2+Datos!$M$2)))) -> 70 | M2: ='Parámetros'!$B$7*('Parámetros'!$B$8*D2+(1-'Parámetros'!$B$8)*E2)+(1-'Parámetros'!$B$7)*('Parámetros'!$B$9*B2+(1-'Parámetros'!$B$9)*C2) -> 70 | N2: ='Parámetros'!$B$10*F2+'Parámetros'!$B$11*G2+(1-'Parámetros'!$B$10-'Parámetros'!$B$11)*H2 -> 70
A3: Software | B3: =MAX(0,MIN(100,'Parámetros'!$B$12+'Parámetros'!$B$13*(Datos!B3-Datos!$B$2))) -> 53.78726 | C3: =MAX(0,MIN(100,'Parámetros'!$B$12+'Parámetros'!$B$13*(Datos!C3-Datos!$C$2))) -> 100 | D3: =MIN(100,2*'Parámetros'!$B$12*Datos!D3/(Datos!D3+Datos!$D$2)) -> 46.545455 | E3: =MIN(100,2*'Parámetros'!$B$12*Datos!E3/(Datos!E3+Datos!$E$2)) -> 70 | F3: =MIN(100,2*'Parámetros'!$B$12*(Datos!G3/Datos!F3)/(Datos!G3/Datos!F3+Datos!$G$2/Datos!$F$2)) -> 73.514684 | G3: =MIN(100,2*'Parámetros'!$B$12*Datos!H3/(Datos!H3+Datos!$H$2)) -> 59.393939 | H3: =MIN(100,2*'Parámetros'!$B$12*Datos!I3/(Datos!I3+Datos!$I$2)) -> 79.133911 | I3: =MIN(100,2*'Parámetros'!$B$12*Datos!$J$2/(Datos!J3+Datos!$J$2)) -> 73.684211 | J3: =MIN(D3,SQRT(D3*I3)) -> 46.545455 | K3: =MAX(0,MIN(100,'Parámetros'!$B$12-'Parámetros'!$B$13*(Datos!K3-Datos!$K$2))) -> 20.872272 | L3: =MAX(0,MIN(100,'Parámetros'!$B$12+'Parámetros'!$B$14*LN((Datos!L3+Datos!M3)/(Datos!$L$2+Datos!$M$2)))) -> 59.798756 | M3: ='Parámetros'!$B$7*('Parámetros'!$B$8*D3+(1-'Parámetros'!$B$8)*E3)+(1-'Parámetros'!$B$7)*('Parámetros'!$B$9*B3+(1-'Parámetros'!$B$9)*C3) -> 55.45697 | N3: ='Parámetros'!$B$10*F3+'Parámetros'!$B$11*G3+(1-'Parámetros'!$B$10-'Parámetros'!$B$11)*H3 -> 69.97723
A4: Enfermería | B4: =MAX(0,MIN(100,'Parámetros'!$B$12+'Parámetros'!$B$13*(Datos!B4-Datos!$B$2))) -> 64.9023 | C4: =MAX(0,MIN(100,'Parámetros'!$B$12+'Parámetros'!$B$13*(Datos!C4-Datos!$C$2))) -> 58.140273 | D4: =MIN(100,2*'Parámetros'!$B$12*Datos!D4/(Datos!D4+Datos!$D$2)) -> 96.334951 | E4: =MIN(100,2*'Parámetros'!$B$12*Datos!E4/(Datos!E4+Datos!$E$2)) -> 67.8125 | F4: =MIN(100,2*'Parámetros'!$B$12*(Datos!G4/Datos!F4)/(Datos!G4/Datos!F4+Datos!$G$2/Datos!$F$2)) -> 6.36444 | G4: =MIN(100,2*'Parámetros'!$B$12*Datos!H4/(Datos!H4+Datos!$H$2)) -> 70.729167 | H4: =MIN(100,2*'Parámetros'!$B$12*Datos!I4/(Datos!I4+Datos!$I$2)) -> 60.126516 | I4: =MIN(100,2*'Parámetros'!$B$12*Datos!$J$2/(Datos!J4+Datos!$J$2)) -> 70 | J4: =MIN(D4,SQRT(D4*I4)) -> 82.118491 | K4: =MAX(0,MIN(100,'Parámetros'!$B$12-'Parámetros'!$B$13*(Datos!K4-Datos!$K$2))) -> 80.527908 | L4: =MAX(0,MIN(100,'Parámetros'!$B$12+'Parámetros'!$B$14*LN((Datos!L4+Datos!M4)/(Datos!$L$2+Datos!$M$2)))) -> 55.356393 | M4: ='Parámetros'!$B$7*('Parámetros'!$B$8*D4+(1-'Parámetros'!$B$8)*E4)+(1-'Parámetros'!$B$7)*('Parámetros'!$B$9*B4+(1-'Parámetros'!$B$9)*C4) -> 82.769551 | N4: ='Parámetros'!$B$10*F4+'Parámetros'!$B$11*G4+(1-'Parámetros'!$B$10-'Parámetros'!$B$11)*H4 -> 42.332613
A5: Medicina | B5: =MAX(0,MIN(100,'Parámetros'!$B$12+'Parámetros'!$B$13*(Datos!B5-Datos!$B$2))) -> 57.04684 | C5: =MAX(0,MIN(100,'Parámetros'!$B$12+'Parámetros'!$B$13*(Datos!C5-Datos!$C$2))) -> 55.779244 | D5: =MIN(100,2*'Parámetros'!$B$12*Datos!D5/(Datos!D5+Datos!$D$2)) -> 93.693694 | E5: =MIN(100,2*'Parámetros'!$B$12*Datos!E5/(Datos!E5+Datos!$E$2)) -> 66.666667 | F5: =MIN(100,2*'Parámetros'!$B$12*(Datos!G5/Datos!F5)/(Datos!G5/Datos!F5+Datos!$G$2/Datos!$F$2)) -> 13.133306 | G5: =MIN(100,2*'Parámetros'!$B$12*Datos!H5/(Datos!H5+Datos!$H$2)) -> 70 | H5: =MIN(100,2*'Parámetros'!$B$12*Datos!I5/(Datos!I5+Datos!$I$2)) -> 75.066207 | I5: =MIN(100,2*'Parámetros'!$B$12*Datos!$J$2/(Datos!J5+Datos!$J$2)) -> 58.333333 | J5: =MIN(D5,SQRT(D5*I5)) -> 73.928786 | K5: =MAX(0,MIN(100,'Parámetros'!$B$12-'Parámetros'!$B$13*(Datos!K5-Datos!$K$2))) -> 59.847241 | L5: =MAX(0,MIN(100,'Parámetros'!$B$12+'Parámetros'!$B$14*LN((Datos!L5+Datos!M5)/(Datos!$L$2+Datos!$M$2)))) -> 41.343179 | M5: ='Parámetros'!$B$7*('Parámetros'!$B$8*D5+(1-'Parámetros'!$B$8)*E5)+(1-'Parámetros'!$B$7)*('Parámetros'!$B$9*B5+(1-'Parámetros'!$B$9)*C5) -> 78.977441 | N5: ='Parámetros'!$B$10*F5+'Parámetros'!$B$11*G5+(1-'Parámetros'!$B$10-'Parámetros'!$B$11)*H5 -> 48.519874
A6: Odontología | B6: =MAX(0,MIN(100,'Parámetros'!$B$12+'Parámetros'!$B$13*(Datos!B6-Datos!$B$2))) -> 58.153867 | C6: =MAX(0,MIN(100,'Parámetros'!$B$12+'Parámetros'!$B$13*(Datos!C6-Datos!$C$2))) -> 58.167445 | D6: =MIN(100,2*'Parámetros'!$B$12*Datos!D6/(Datos!D6+Datos!$D$2)) -> 93.930858 | E6: =MIN(100,2*'Parámetros'!$B$12*Datos!E6/(Datos!E6+Datos!$E$2)) -> 66.666667 | F6: =MIN(100,2*'Parámetros'!$B$12*(Datos!G6/Datos!F6)/(Datos!G6/Datos!F6+Datos!$G$2/Datos!$F$2)) -> 10.434783 | G6: =MIN(100,2*'Parámetros'!$B$12*Datos!H6/(Datos!H6+Datos!$H$2)) -> 68.108108 | H6: =MIN(100,2*'Parámetros'!$B$12*Datos!I6/(Datos!I6+Datos!$I$2)) -> 75.066207 | I6: =MIN(100,2*'Parámetros'!$B$12*Datos!$J$2/(Datos!J6+Datos!$J$2)) -> 63.636364 | J6: =MIN(D6,SQRT(D6*I6)) -> 77.313765 | K6: =MAX(0,MIN(100,'Parámetros'!$B$12-'Parámetros'!$B$13*(Datos!K6-Datos!$K$2))) -> 67.671108 | L6: =MAX(0,MIN(100,'Parámetros'!$B$12+'Parámetros'!$B$14*LN((Datos!L6+Datos!M6)/(Datos!$L$2+Datos!$M$2)))) -> 4.5076234 | M6: ='Parámetros'!$B$7*('Parámetros'!$B$8*D6+(1-'Parámetros'!$B$8)*E6)+(1-'Parámetros'!$B$7)*('Parámetros'!$B$9*B6+(1-'Parámetros'!$B$9)*C6) -> 79.638164 | N6: ='Parámetros'!$B$10*F6+'Parámetros'!$B$11*G6+(1-'Parámetros'!$B$10-'Parámetros'!$B$11)*H6 -> 46.778303
A7: Multimedia y produccion audiovisual | B7: =MAX(0,MIN(100,'Parámetros'!$B$12+'Parámetros'!$B$13*(Datos!B7-Datos!$B$2))) -> 83.826395 | C7: =MAX(0,MIN(100,'Parámetros'!$B$12+'Parámetros'!$B$13*(Datos!C7-Datos!$C$2))) -> 42.239424 | D7: =MIN(100,2*'Parámetros'!$B$12*Datos!D7/(Datos!D7+Datos!$D$2)) -> 56.130536 | E7: =MIN(100,2*'Parámetros'!$B$12*Datos!E7/(Datos!E7+Datos!$E$2)) -> 68.923077 | F7: =MIN(100,2*'Parámetros'!$B$12*(Datos!G7/Datos!F7)/(Datos!G7/Datos!F7+Datos!$G$2/Datos!$F$2)) -> 15.537971 | G7: =MIN(100,2*'Parámetros'!$B$12*Datos!H7/(Datos!H7+Datos!$H$2)) -> 66.111111 | H7: =MIN(100,2*'Parámetros'!$B$12*Datos!I7/(Datos!I7+Datos!$I$2)) -> 62.145773 | I7: =MIN(100,2*'Parámetros'!$B$12*Datos!$J$2/(Datos!J7+Datos!$J$2)) -> 93.333333 | J7: =MIN(D7,SQRT(D7*I7)) -> 56.130536 | K7: =MAX(0,MIN(100,'Parámetros'!$B$12-'Parámetros'!$B$13*(Datos!K7-Datos!$K$2))) -> 43.157927 | L7: =MAX(0,MIN(100,'Parámetros'!$B$12+'Parámetros'!$B$14*LN((Datos!L7+Datos!M7)/(Datos!$L$2+Datos!$M$2)))) -> 20.895886 | M7: ='Parámetros'!$B$7*('Parámetros'!$B$8*D7+(1-'Parámetros'!$B$8)*E7)+(1-'Parámetros'!$B$7)*('Parámetros'!$B$9*B7+(1-'Parámetros'!$B$9)*C7) -> 62.28897 | N7: ='Parámetros'!$B$10*F7+'Parámetros'!$B$11*G7+(1-'Parámetros'!$B$10-'Parámetros'!$B$11)*H7 -> 44.890521
A8: Derecho | B8: =MAX(0,MIN(100,'Parámetros'!$B$12+'Parámetros'!$B$13*(Datos!B8-Datos!$B$2))) -> 58.145545 | C8: =MAX(0,MIN(100,'Parámetros'!$B$12+'Parámetros'!$B$13*(Datos!C8-Datos!$C$2))) -> 69.559312 | D8: =MIN(100,2*'Parámetros'!$B$12*Datos!D8/(Datos!D8+Datos!$D$2)) -> 89.537167 | E8: =MIN(100,2*'Parámetros'!$B$12*Datos!E8/(Datos!E8+Datos!$E$2)) -> 66.666667 | F8: =MIN(100,2*'Parámetros'!$B$12*(Datos!G8/Datos!F8)/(Datos!G8/Datos!F8+Datos!$G$2/Datos!$F$2)) -> 4.8214286 | G8: =MIN(100,2*'Parámetros'!$B$12*Datos!H8/(Datos!H8+Datos!$H$2)) -> 70.729167 | H8: =MIN(100,2*'Parámetros'!$B$12*Datos!I8/(Datos!I8+Datos!$I$2)) -> 59.307176 | I8: =MIN(100,2*'Parámetros'!$B$12*Datos!$J$2/(Datos!J8+Datos!$J$2)) -> 56 | J8: =MIN(D8,SQRT(D8*I8)) -> 70.810178 | K8: =MAX(0,MIN(100,'Parámetros'!$B$12-'Parámetros'!$B$13*(Datos!K8-Datos!$K$2))) -> 46.141479 | L8: =MAX(0,MIN(100,'Parámetros'!$B$12+'Parámetros'!$B$14*LN((Datos!L8+Datos!M8)/(Datos!$L$2+Datos!$M$2)))) -> 94.935987 | M8: ='Parámetros'!$B$7*('Parámetros'!$B$8*D8+(1-'Parámetros'!$B$8)*E8)+(1-'Parámetros'!$B$7)*('Parámetros'!$B$9*B8+(1-'Parámetros'!$B$9)*C8) -> 78.261962 | N8: ='Parámetros'!$B$10*F8+'Parámetros'!$B$11*G8+(1-'Parámetros'!$B$10-'Parámetros'!$B$11)*H8 -> 41.510574
A9: Arquitectura | B9: =MAX(0,MIN(100,'Parámetros'!$B$12+'Parámetros'!$B$13*(Datos!B9-Datos!$B$2))) -> 56.924065 | C9: =MAX(0,MIN(100,'Parámetros'!$B$12+'Parámetros'!$B$13*(Datos!C9-Datos!$C$2))) -> 63.245314 | D9: =MIN(100,2*'Parámetros'!$B$12*Datos!D9/(Datos!D9+Datos!$D$2)) -> 88.304598 | E9: =MIN(100,2*'Parámetros'!$B$12*Datos!E9/(Datos!E9+Datos!$E$2)) -> 67.8125 | F9: =MIN(100,2*'Parámetros'!$B$12*(Datos!G9/Datos!F9)/(Datos!G9/Datos!F9+Datos!$G$2/Datos!$F$2)) -> 13.993003 | G9: =MIN(100,2*'Parámetros'!$B$12*Datos!H9/(Datos!H9+Datos!$H$2)) -> 64.858757 | H9: =MIN(100,2*'Parámetros'!$B$12*Datos!I9/(Datos!I9+Datos!$I$2)) -> 63.045092 | I9: =MIN(100,2*'Parámetros'!$B$12*Datos!$J$2/(Datos!J9+Datos!$J$2)) -> 66.666667 | J9: =MIN(D9,SQRT(D9*I9)) -> 76.726613 | K9: =MAX(0,MIN(100,'Parámetros'!$B$12-'Parámetros'!$B$13*(Datos!K9-Datos!$K$2))) -> 69.536899 | L9: =MAX(0,MIN(100,'Parámetros'!$B$12+'Parámetros'!$B$14*LN((Datos!L9+Datos!M9)/(Datos!$L$2+Datos!$M$2)))) -> 76.308119 | M9: ='Parámetros'!$B$7*('Parámetros'!$B$8*D9+(1-'Parámetros'!$B$8)*E9)+(1-'Parámetros'!$B$7)*('Parámetros'!$B$9*B9+(1-'Parámetros'!$B$9)*C9) -> 76.653156 | N9: ='Parámetros'!$B$10*F9+'Parámetros'!$B$11*G9+(1-'Parámetros'!$B$10-'Parámetros'!$B$11)*H9 -> 44.059039
A10: RRII | B10: =MAX(0,MIN(100,'Parámetros'!$B$12+'Parámetros'!$B$13*(Datos!B10-Datos!$B$2))) -> 56.940162 | C10: =MAX(0,MIN(100,'Parámetros'!$B$12+'Parámetros'!$B$13*(Datos!C10-Datos!$C$2))) -> 70.923124 | D10: =MIN(100,2*'Parámetros'!$B$12*Datos!D10/(Datos!D10+Datos!$D$2)) -> 38.647887 | E10: =MIN(100,2*'Parámetros'!$B$12*Datos!E10/(Datos!E10+Datos!$E$2)) -> 70 | F10: =MIN(100,2*'Parámetros'!$B$12*(Datos!G10/Datos!F10)/(Datos!G10/Datos!F10+Datos!$G$2/Datos!$F$2)) -> 68.292683 | G10: =MIN(100,2*'Parámetros'!$B$12*Datos!H10/(Datos!H10+Datos!$H$2)) -> 70.729167 | H10: =MIN(100,2*'Parámetros'!$B$12*Datos!I10/(Datos!I10+Datos!$I$2)) -> 84.959511 | I10: =MIN(100,2*'Parámetros'!$B$12*Datos!$J$2/(Datos!J10+Datos!$J$2)) -> 87.5 | J10: =MIN(D10,SQRT(D10*I10)) -> 38.647887 | K10: =MAX(0,MIN(100,'Parámetros'!$B$12-'Parámetros'!$B$13*(Datos!K10-Datos!$K$2))) -> 68.866207 | L10: =MAX(0,MIN(100,'Parámetros'!$B$12+'Parámetros'!$B$14*LN((Datos!L10+Datos!M10)/(Datos!$L$2+Datos!$M$2)))) -> 0 | M10: ='Parámetros'!$B$7*('Parámetros'!$B$8*D10+(1-'Parámetros'!$B$8)*E10)+(1-'Parámetros'!$B$7)*('Parámetros'!$B$9*B10+(1-'Parámetros'!$B$9)*C10) -> 48.556282 | N10: ='Parámetros'!$B$10*F10+'Parámetros'!$B$11*G10+(1-'Parámetros'!$B$10-'Parámetros'!$B$11)*H10 -> 73.312159
A11: Gastronomía | B11: =MAX(0,MIN(100,'Parámetros'!$B$12+'Parámetros'!$B$13*(Datos!B11-Datos!$B$2))) -> 59.615824 | C11: =MAX(0,MIN(100,'Parámetros'!$B$12+'Parámetros'!$B$13*(Datos!C11-Datos!$C$2))) -> 59.978515 | D11: =MIN(100,2*'Parámetros'!$B$12*Datos!D11/(Datos!D11+Datos!$D$2)) -> 86.617211 | E11: =MIN(100,2*'Parámetros'!$B$12*Datos!E11/(Datos!E11+Datos!$E$2)) -> 66.666667 | F11: =MIN(100,2*'Parámetros'!$B$12*(Datos!G11/Datos!F11)/(Datos!G11/Datos!F11+Datos!$G$2/Datos!$F$2)) -> 14.225233 | G11: =MIN(100,2*'Parámetros'!$B$12*Datos!H11/(Datos!H11+Datos!$H$2)) -> 68.108108 | H11: =MIN(100,2*'Parámetros'!$B$12*Datos!I11/(Datos!I11+Datos!$I$2)) -> 51.859928 | I11: =MIN(100,2*'Parámetros'!$B$12*Datos!$J$2/(Datos!J11+Datos!$J$2)) -> 70 | J11: =MIN(D11,SQRT(D11*I11)) -> 77.866583 | K11: =MAX(0,MIN(100,'Parámetros'!$B$12-'Parámetros'!$B$13*(Datos!K11-Datos!$K$2))) -> 42.671346 | L11: =MAX(0,MIN(100,'Parámetros'!$B$12+'Parámetros'!$B$14*LN((Datos!L11+Datos!M11)/(Datos!$L$2+Datos!$M$2)))) -> 57.299743 | M11: ='Parámetros'!$B$7*('Parámetros'!$B$8*D11+(1-'Parámetros'!$B$8)*E11)+(1-'Parámetros'!$B$7)*('Parámetros'!$B$9*B11+(1-'Parámetros'!$B$9)*C11) -> 75.908022 | N11: ='Parámetros'!$B$10*F11+'Parámetros'!$B$11*G11+(1-'Parámetros'!$B$10-'Parámetros'!$B$11)*H11 -> 42.492913
A12: Música | B12: =MAX(0,MIN(100,'Parámetros'!$B$12+'Parámetros'!$B$13*(Datos!B12-Datos!$B$2))) -> 25.758535 | C12: =MAX(0,MIN(100,'Parámetros'!$B$12+'Parámetros'!$B$13*(Datos!C12-Datos!$C$2))) -> 36.140229 | D12: =MIN(100,2*'Parámetros'!$B$12*Datos!D12/(Datos!D12+Datos!$D$2)) -> 73.246753 | E12: =MIN(100,2*'Parámetros'!$B$12*Datos!E12/(Datos!E12+Datos!$E$2)) -> 68.923077 | F12: =MIN(100,2*'Parámetros'!$B$12*(Datos!G12/Datos!F12)/(Datos!G12/Datos!F12+Datos!$G$2/Datos!$F$2)) -> 4.3636364 | G12: =MIN(100,2*'Parámetros'!$B$12*Datos!H12/(Datos!H12+Datos!$H$2)) -> 66.111111 | H12: =MIN(100,2*'Parámetros'!$B$12*Datos!I12/(Datos!I12+Datos!$I$2)) -> 65.159039 | I12: =MIN(100,2*'Parámetros'!$B$12*Datos!$J$2/(Datos!J12+Datos!$J$2)) -> 100 | J12: =MIN(D12,SQRT(D12*I12)) -> 73.246753 | K12: =MAX(0,MIN(100,'Parámetros'!$B$12-'Parámetros'!$B$13*(Datos!K12-Datos!$K$2))) -> 81.78335 | L12: =MAX(0,MIN(100,'Parámetros'!$B$12+'Parámetros'!$B$14*LN((Datos!L12+Datos!M12)/(Datos!$L$2+Datos!$M$2)))) -> 0 | M12: ='Parámetros'!$B$7*('Parámetros'!$B$8*D12+(1-'Parámetros'!$B$8)*E12)+(1-'Parámetros'!$B$7)*('Parámetros'!$B$9*B12+(1-'Parámetros'!$B$9)*C12) -> 57.434916 | N12: ='Parámetros'!$B$10*F12+'Parámetros'!$B$11*G12+(1-'Parámetros'!$B$10-'Parámetros'!$B$11)*H12 -> 41.174103
A13: Psicología | B13: =MAX(0,MIN(100,'Parámetros'!$B$12+'Parámetros'!$B$13*(Datos!B13-Datos!$B$2))) -> 58.669377 | C13: =MAX(0,MIN(100,'Parámetros'!$B$12+'Parámetros'!$B$13*(Datos!C13-Datos!$C$2))) -> 65.282132 | D13: =MIN(100,2*'Parámetros'!$B$12*Datos!D13/(Datos!D13+Datos!$D$2)) -> 79.832776 | E13: =MIN(100,2*'Parámetros'!$B$12*Datos!E13/(Datos!E13+Datos!$E$2)) -> 67.8125 | F13: =MIN(100,2*'Parámetros'!$B$12*(Datos!G13/Datos!F13)/(Datos!G13/Datos!F13+Datos!$G$2/Datos!$F$2)) -> 6.8108108 | G13: =MIN(100,2*'Parámetros'!$B$12*Datos!H13/(Datos!H13+Datos!$H$2)) -> 66.111111 | H13: =MIN(100,2*'Parámetros'!$B$12*Datos!I13/(Datos!I13+Datos!$I$2)) -> 59.580426 | I13: =MIN(100,2*'Parámetros'!$B$12*Datos!$J$2/(Datos!J13+Datos!$J$2)) -> 60.869565 | J13: =MIN(D13,SQRT(D13*I13)) -> 69.709299 | K13: =MAX(0,MIN(100,'Parámetros'!$B$12-'Parámetros'!$B$13*(Datos!K13-Datos!$K$2))) -> 60.057206 | L13: =MAX(0,MIN(100,'Parámetros'!$B$12+'Parámetros'!$B$14*LN((Datos!L13+Datos!M13)/(Datos!$L$2+Datos!$M$2)))) -> 36.157857 | M13: ='Parámetros'!$B$7*('Parámetros'!$B$8*D13+(1-'Parámetros'!$B$8)*E13)+(1-'Parámetros'!$B$7)*('Parámetros'!$B$9*B13+(1-'Parámetros'!$B$9)*C13) -> 72.338608 | N13: ='Parámetros'!$B$10*F13+'Parámetros'!$B$11*G13+(1-'Parámetros'!$B$10-'Parámetros'!$B$11)*H13 -> 40.75832

Sheet Resultados
A1: Carrera | B1: Demanda 30% | C1: Empleabilidad 22% | D1: Oportunidad 28% | E1: Precio 12% | F1: Sector 8% | G1: Índice /100 | H1: Diferencia vs referencia | I1: Clasificación provisional | J1: Señal de oportunidad | K1: Estado
A2: Negocios Internacionales | B2: =Puntajes!M2 -> 70 | C2: =Puntajes!N2 -> 70 | D2: =Puntajes!J2 -> 70 | E2: =Puntajes!K2 -> 70 | F2: =Puntajes!L2 -> 70 | G2: =B2*'Parámetros'!$B$2+C2*'Parámetros'!$B$3+D2*'Parámetros'!$B$4+E2*'Parámetros'!$B$5+F2*'Parámetros'!$B$6 -> 70 | H2: =G2-$G$2 -> 0 | I2: =IF(G2>='Parámetros'!$B$15,"Superior a referencia",IF(G2>='Parámetros'!$B$16,"Cercano a referencia",IF(G2>='Parámetros'!$B$17,"Inferior: requiere ajustes","Rezago importante"))) -> Cercano a referencia | J2: =IF(AND(Datos!D2>=Datos!$D$2*'Parámetros'!$B$18,Datos!J2<=Datos!$J$2*'Parámetros'!$B$19,C2>='Parámetros'!$B$20,E2>='Parámetros'!$B$20),"Oportunidad prioritaria condicionada",IF(Datos!D2>=Datos!$D$2,IF(Datos!J2>Datos!$J$2,"Demanda alta / competencia alta","Demanda alta / competencia baja o igual"),IF(Datos!J2>Datos!$J$2,"Demanda baja / competencia alta","Demanda baja / competencia baja o igual"))) -> Demanda alta / competencia baja o igual | K2: Exploratorio: validar fuentes y escalas
A3: Software | B3: =Puntajes!M3 -> 55.45697 | C3: =Puntajes!N3 -> 69.97723 | D3: =Puntajes!J3 -> 46.545455 | E3: =Puntajes!K3 -> 20.872272 | F3: =Puntajes!L3 -> 59.798756 | G3: =B3*'Parámetros'!$B$2+C3*'Parámetros'!$B$3+D3*'Parámetros'!$B$4+E3*'Parámetros'!$B$5+F3*'Parámetros'!$B$6 -> 52.353382 | H3: =G3-$G$2 -> -17.646618 | I3: =IF(G3>='Parámetros'!$B$15,"Superior a referencia",IF(G3>='Parámetros'!$B$16,"Cercano a referencia",IF(G3>='Parámetros'!$B$17,"Inferior: requiere ajustes","Rezago importante"))) -> Inferior: requiere ajustes | J3: =IF(AND(Datos!D3>=Datos!$D$2*'Parámetros'!$B$18,Datos!J3<=Datos!$J$2*'Parámetros'!$B$19,C3>='Parámetros'!$B$20,E3>='Parámetros'!$B$20),"Oportunidad prioritaria condicionada",IF(Datos!D3>=Datos!$D$2,IF(Datos!J3>Datos!$J$2,"Demanda alta / competencia alta","Demanda alta / competencia baja o igual"),IF(Datos!J3>Datos!$J$2,"Demanda baja / competencia alta","Demanda baja / competencia baja o igual"))) -> Demanda baja / competencia baja o igual | K3: Exploratorio: validar fuentes y escalas
A4: Enfermería | B4: =Puntajes!M4 -> 82.769551 | C4: =Puntajes!N4 -> 42.332613 | D4: =Puntajes!J4 -> 82.118491 | E4: =Puntajes!K4 -> 80.527908 | F4: =Puntajes!L4 -> 55.356393 | G4: =B4*'Parámetros'!$B$2+C4*'Parámetros'!$B$3+D4*'Parámetros'!$B$4+E4*'Parámetros'!$B$5+F4*'Parámetros'!$B$6 -> 71.229078 | H4: =G4-$G$2 -> 1.2290784 | I4: =IF(G4>='Parámetros'!$B$15,"Superior a referencia",IF(G4>='Parámetros'!$B$16,"Cercano a referencia",IF(G4>='Parámetros'!$B$17,"Inferior: requiere ajustes","Rezago importante"))) -> Cercano a referencia | J4: =IF(AND(Datos!D4>=Datos!$D$2*'Parámetros'!$B$18,Datos!J4<=Datos!$J$2*'Parámetros'!$B$19,C4>='Parámetros'!$B$20,E4>='Parámetros'!$B$20),"Oportunidad prioritaria condicionada",IF(Datos!D4>=Datos!$D$2,IF(Datos!J4>Datos!$J$2,"Demanda alta / competencia alta","Demanda alta / competencia baja o igual"),IF(Datos!J4>Datos!$J$2,"Demanda baja / competencia alta","Demanda baja / competencia baja o igual"))) -> Demanda alta / competencia baja o igual | K4: Exploratorio: validar fuentes y escalas
A5: Medicina | B5: =Puntajes!M5 -> 78.977441 | C5: =Puntajes!N5 -> 48.519874 | D5: =Puntajes!J5 -> 73.928786 | E5: =Puntajes!K5 -> 59.847241 | F5: =Puntajes!L5 -> 41.343179 | G5: =B5*'Parámetros'!$B$2+C5*'Parámetros'!$B$3+D5*'Parámetros'!$B$4+E5*'Parámetros'!$B$5+F5*'Parámetros'!$B$6 -> 65.556788 | H5: =G5-$G$2 -> -4.4432121 | I5: =IF(G5>='Parámetros'!$B$15,"Superior a referencia",IF(G5>='Parámetros'!$B$16,"Cercano a referencia",IF(G5>='Parámetros'!$B$17,"Inferior: requiere ajustes","Rezago importante"))) -> Cercano a referencia | J5: =IF(AND(Datos!D5>=Datos!$D$2*'Parámetros'!$B$18,Datos!J5<=Datos!$J$2*'Parámetros'!$B$19,C5>='Parámetros'!$B$20,E5>='Parámetros'!$B$20),"Oportunidad prioritaria condicionada",IF(Datos!D5>=Datos!$D$2,IF(Datos!J5>Datos!$J$2,"Demanda alta / competencia alta","Demanda alta / competencia baja o igual"),IF(Datos!J5>Datos!$J$2,"Demanda baja / competencia alta","Demanda baja / competencia baja o igual"))) -> Demanda alta / competencia alta | K5: Exploratorio: validar fuentes y escalas
A6: Odontología | B6: =Puntajes!M6 -> 79.638164 | C6: =Puntajes!N6 -> 46.778303 | D6: =Puntajes!J6 -> 77.313765 | E6: =Puntajes!K6 -> 67.671108 | F6: =Puntajes!L6 -> 4.5076234 | G6: =B6*'Parámetros'!$B$2+C6*'Parámetros'!$B$3+D6*'Parámetros'!$B$4+E6*'Parámetros'!$B$5+F6*'Parámetros'!$B$6 -> 64.311673 | H6: =G6-$G$2 -> -5.6883271 | I6: =IF(G6>='Parámetros'!$B$15,"Superior a referencia",IF(G6>='Parámetros'!$B$16,"Cercano a referencia",IF(G6>='Parámetros'!$B$17,"Inferior: requiere ajustes","Rezago importante"))) -> Inferior: requiere ajustes | J6: =IF(AND(Datos!D6>=Datos!$D$2*'Parámetros'!$B$18,Datos!J6<=Datos!$J$2*'Parámetros'!$B$19,C6>='Parámetros'!$B$20,E6>='Parámetros'!$B$20),"Oportunidad prioritaria condicionada",IF(Datos!D6>=Datos!$D$2,IF(Datos!J6>Datos!$J$2,"Demanda alta / competencia alta","Demanda alta / competencia baja o igual"),IF(Datos!J6>Datos!$J$2,"Demanda baja / competencia alta","Demanda baja / competencia baja o igual"))) -> Demanda alta / competencia alta | K6: Exploratorio: validar fuentes y escalas
A7: Multimedia y produccion audiovisual | B7: =Puntajes!M7 -> 62.28897 | C7: =Puntajes!N7 -> 44.890521 | D7: =Puntajes!J7 -> 56.130536 | E7: =Puntajes!K7 -> 43.157927 | F7: =Puntajes!L7 -> 20.895886 | G7: =B7*'Parámetros'!$B$2+C7*'Parámetros'!$B$3+D7*'Parámetros'!$B$4+E7*'Parámetros'!$B$5+F7*'Parámetros'!$B$6 -> 51.129778 | H7: =G7-$G$2 -> -18.870222 | I7: =IF(G7>='Parámetros'!$B$15,"Superior a referencia",IF(G7>='Parámetros'!$B$16,"Cercano a referencia",IF(G7>='Parámetros'!$B$17,"Inferior: requiere ajustes","Rezago importante"))) -> Inferior: requiere ajustes | J7: =IF(AND(Datos!D7>=Datos!$D$2*'Parámetros'!$B$18,Datos!J7<=Datos!$J$2*'Parámetros'!$B$19,C7>='Parámetros'!$B$20,E7>='Parámetros'!$B$20),"Oportunidad prioritaria condicionada",IF(Datos!D7>=Datos!$D$2,IF(Datos!J7>Datos!$J$2,"Demanda alta / competencia alta","Demanda alta / competencia baja o igual"),IF(Datos!J7>Datos!$J$2,"Demanda baja / competencia alta","Demanda baja / competencia baja o igual"))) -> Demanda baja / competencia baja o igual | K7: Exploratorio: validar fuentes y escalas
A8: Derecho | B8: =Puntajes!M8 -> 78.261962 | C8: =Puntajes!N8 -> 41.510574 | D8: =Puntajes!J8 -> 70.810178 | E8: =Puntajes!K8 -> 46.141479 | F8: =Puntajes!L8 -> 94.935987 | G8: =B8*'Parámetros'!$B$2+C8*'Parámetros'!$B$3+D8*'Parámetros'!$B$4+E8*'Parámetros'!$B$5+F8*'Parámetros'!$B$6 -> 65.569621 | H8: =G8-$G$2 -> -4.4303787 | I8: =IF(G8>='Parámetros'!$B$15,"Superior a referencia",IF(G8>='Parámetros'!$B$16,"Cercano a referencia",IF(G8>='Parámetros'!$B$17,"Inferior: requiere ajustes","Rezago importante"))) -> Cercano a referencia | J8: =IF(AND(Datos!D8>=Datos!$D$2*'Parámetros'!$B$18,Datos!J8<=Datos!$J$2*'Parámetros'!$B$19,C8>='Parámetros'!$B$20,E8>='Parámetros'!$B$20),"Oportunidad prioritaria condicionada",IF(Datos!D8>=Datos!$D$2,IF(Datos!J8>Datos!$J$2,"Demanda alta / competencia alta","Demanda alta / competencia baja o igual"),IF(Datos!J8>Datos!$J$2,"Demanda baja / competencia alta","Demanda baja / competencia baja o igual"))) -> Demanda alta / competencia alta | K8: Exploratorio: validar fuentes y escalas
A9: Arquitectura | B9: =Puntajes!M9 -> 76.653156 | C9: =Puntajes!N9 -> 44.059039 | D9: =Puntajes!J9 -> 76.726613 | E9: =Puntajes!K9 -> 69.536899 | F9: =Puntajes!L9 -> 76.308119 | G9: =B9*'Parámetros'!$B$2+C9*'Parámetros'!$B$3+D9*'Parámetros'!$B$4+E9*'Parámetros'!$B$5+F9*'Parámetros'!$B$6 -> 68.621465 | H9: =G9-$G$2 -> -1.3785354 | I9: =IF(G9>='Parámetros'!$B$15,"Superior a referencia",IF(G9>='Parámetros'!$B$16,"Cercano a referencia",IF(G9>='Parámetros'!$B$17,"Inferior: requiere ajustes","Rezago importante"))) -> Cercano a referencia | J9: =IF(AND(Datos!D9>=Datos!$D$2*'Parámetros'!$B$18,Datos!J9<=Datos!$J$2*'Parámetros'!$B$19,C9>='Parámetros'!$B$20,E9>='Parámetros'!$B$20),"Oportunidad prioritaria condicionada",IF(Datos!D9>=Datos!$D$2,IF(Datos!J9>Datos!$J$2,"Demanda alta / competencia alta","Demanda alta / competencia baja o igual"),IF(Datos!J9>Datos!$J$2,"Demanda baja / competencia alta","Demanda baja / competencia baja o igual"))) -> Demanda alta / competencia alta | K9: Exploratorio: validar fuentes y escalas
A10: RRII | B10: =Puntajes!M10 -> 48.556282 | C10: =Puntajes!N10 -> 73.312159 | D10: =Puntajes!J10 -> 38.647887 | E10: =Puntajes!K10 -> 68.866207 | F10: =Puntajes!L10 -> 0 | G10: =B10*'Parámetros'!$B$2+C10*'Parámetros'!$B$3+D10*'Parámetros'!$B$4+E10*'Parámetros'!$B$5+F10*'Parámetros'!$B$6 -> 49.780913 | H10: =G10-$G$2 -> -20.219087 | I10: =IF(G10>='Parámetros'!$B$15,"Superior a referencia",IF(G10>='Parámetros'!$B$16,"Cercano a referencia",IF(G10>='Parámetros'!$B$17,"Inferior: requiere ajustes","Rezago importante"))) -> Rezago importante | J10: =IF(AND(Datos!D10>=Datos!$D$2*'Parámetros'!$B$18,Datos!J10<=Datos!$J$2*'Parámetros'!$B$19,C10>='Parámetros'!$B$20,E10>='Parámetros'!$B$20),"Oportunidad prioritaria condicionada",IF(Datos!D10>=Datos!$D$2,IF(Datos!J10>Datos!$J$2,"Demanda alta / competencia alta","Demanda alta / competencia baja o igual"),IF(Datos!J10>Datos!$J$2,"Demanda baja / competencia alta","Demanda baja / competencia baja o igual"))) -> Demanda baja / competencia baja o igual | K10: Exploratorio: validar fuentes y escalas
A11: Gastronomía | B11: =Puntajes!M11 -> 75.908022 | C11: =Puntajes!N11 -> 42.492913 | D11: =Puntajes!J11 -> 77.866583 | E11: =Puntajes!K11 -> 42.671346 | F11: =Puntajes!L11 -> 57.299743 | G11: =B11*'Parámetros'!$B$2+C11*'Parámetros'!$B$3+D11*'Parámetros'!$B$4+E11*'Parámetros'!$B$5+F11*'Parámetros'!$B$6 -> 63.628032 | H11: =G11-$G$2 -> -6.3719682 | I11: =IF(G11>='Parámetros'!$B$15,"Superior a referencia",IF(G11>='Parámetros'!$B$16,"Cercano a referencia",IF(G11>='Parámetros'!$B$17,"Inferior: requiere ajustes","Rezago importante"))) -> Inferior: requiere ajustes | J11: =IF(AND(Datos!D11>=Datos!$D$2*'Parámetros'!$B$18,Datos!J11<=Datos!$J$2*'Parámetros'!$B$19,C11>='Parámetros'!$B$20,E11>='Parámetros'!$B$20),"Oportunidad prioritaria condicionada",IF(Datos!D11>=Datos!$D$2,IF(Datos!J11>Datos!$J$2,"Demanda alta / competencia alta","Demanda alta / competencia baja o igual"),IF(Datos!J11>Datos!$J$2,"Demanda baja / competencia alta","Demanda baja / competencia baja o igual"))) -> Demanda alta / competencia baja o igual | K11: Exploratorio: validar fuentes y escalas
A12: Música | B12: =Puntajes!M12 -> 57.434916 | C12: =Puntajes!N12 -> 41.174103 | D12: =Puntajes!J12 -> 73.246753 | E12: =Puntajes!K12 -> 81.78335 | F12: =Puntajes!L12 -> 0 | G12: =B12*'Parámetros'!$B$2+C12*'Parámetros'!$B$3+D12*'Parámetros'!$B$4+E12*'Parámetros'!$B$5+F12*'Parámetros'!$B$6 -> 56.61187 | H12: =G12-$G$2 -> -13.38813 | I12: =IF(G12>='Parámetros'!$B$15,"Superior a referencia",IF(G12>='Parámetros'!$B$16,"Cercano a referencia",IF(G12>='Parámetros'!$B$17,"Inferior: requiere ajustes","Rezago importante"))) -> Inferior: requiere ajustes | J12: =IF(AND(Datos!D12>=Datos!$D$2*'Parámetros'!$B$18,Datos!J12<=Datos!$J$2*'Parámetros'!$B$19,C12>='Parámetros'!$B$20,E12>='Parámetros'!$B$20),"Oportunidad prioritaria condicionada",IF(Datos!D12>=Datos!$D$2,IF(Datos!J12>Datos!$J$2,"Demanda alta / competencia alta","Demanda alta / competencia baja o igual"),IF(Datos!J12>Datos!$J$2,"Demanda baja / competencia alta","Demanda baja / competencia baja o igual"))) -> Demanda alta / competencia baja o igual | K12: Exploratorio: validar fuentes y escalas
A13: Psicología | B13: =Puntajes!M13 -> 72.338608 | C13: =Puntajes!N13 -> 40.75832 | D13: =Puntajes!J13 -> 69.709299 | E13: =Puntajes!K13 -> 60.057206 | F13: =Puntajes!L13 -> 36.157857 | G13: =B13*'Parámetros'!$B$2+C13*'Parámetros'!$B$3+D13*'Parámetros'!$B$4+E13*'Parámetros'!$B$5+F13*'Parámetros'!$B$6 -> 60.28651 | H13: =G13-$G$2 -> -9.7134904 | I13: =IF(G13>='Parámetros'!$B$15,"Superior a referencia",IF(G13>='Parámetros'!$B$16,"Cercano a referencia",IF(G13>='Parámetros'!$B$17,"Inferior: requiere ajustes","Rezago importante"))) -> Inferior: requiere ajustes | J13: =IF(AND(Datos!D13>=Datos!$D$2*'Parámetros'!$B$18,Datos!J13<=Datos!$J$2*'Parámetros'!$B$19,C13>='Parámetros'!$B$20,E13>='Parámetros'!$B$20),"Oportunidad prioritaria condicionada",IF(Datos!D13>=Datos!$D$2,IF(Datos!J13>Datos!$J$2,"Demanda alta / competencia alta","Demanda alta / competencia baja o igual"),IF(Datos!J13>Datos!$J$2,"Demanda baja / competencia alta","Demanda baja / competencia baja o igual"))) -> Demanda alta / competencia alta | K13: Exploratorio: validar fuentes y escalas
